kubewatcher/__init__.py
kubewatcher/cli.py
kubewatcher/filter.py
kubewatcher/handlers.py
kubewatcher/kubewatcher.py
kubewatcher/parse_config_files.py
kubewatcher/path_extractor.py
kubewatcher/thread_launcher.py
tests/__init__.py
tests/test_filters.py
tests/test_handlers__handle.py
tests/test_handlers__post_message_to_slack.py
tests/test_handlers__post_message_to_telegram.py
tests/test_handlers__send_mail.py
tests/test_kubewatcher__generate_message.py
tests/test_kubewatcher__trigger.py
tests/test_path_extractor__evaluate_path.py
tests/test_path_extractor__extract_value.py
tests/test_path_extractor__extract_values.py
kubewatcher-1.7.1.dist-info/METADATA
kubewatcher-1.7.1.dist-info/WHEEL
kubewatcher-1.7.1.dist-info/entry_points.txt
kubewatcher-1.7.1.dist-info/top_level.txt
kubewatcher-1.7.1.dist-info/RECORD
