Metadata-Version: 2.1
Name: kubewatcher
Version: 1.7.1
Summary: Please see https://github.com/tonsV2/kubewatcher for details
Home-page: UNKNOWN
License: UNKNOWN
Platform: UNKNOWN
Requires-Python: >=3.7
Requires-Dist: kubernetes (~=12.0.1)
Requires-Dist: envyaml (~=1.1.201202)
Requires-Dist: twine (~=3.3.0)
Requires-Dist: click (~=7.1.2)
Requires-Dist: yamlpath (~=3.4.0)
